hamtools/__init__.py
hamtools/adif.py
hamtools/ctydat.py
hamtools/geolog.py
hamtools/kml.py
hamtools/qrz.py
hamtools/ziplocs.py
hamtools/ctydat/cty.dat
hamtools-0.3.data/scripts/geolog
hamtools-0.3.data/scripts/vk
hamtools-0.3.dist-info/DESCRIPTION.rst
hamtools-0.3.dist-info/METADATA
hamtools-0.3.dist-info/RECORD
hamtools-0.3.dist-info/WHEEL
hamtools-0.3.dist-info/metadata.json
hamtools-0.3.dist-info/top_level.txt
