Metadata-Version: 2.0
Name: hamtools
Version: 0.3
Summary: N1YWB Python Ham Radio Tools
Home-page: https://github.com/n1ywb/python-hamtools
Author: Jeff Laughlin
Author-email: jeff@jefflaughlinconsulting.com
License: UNKNOWN
Download-URL: https://github.com/n1ywb/python-hamtools/archive/0.3.zip
Keywords: ham,amateur,qrz,adif,cabrillo,kml,geojson,ctydat
Platform: UNKNOWN
Requires-Dist: geojson
Requires-Dist: requests
Requires-Dist: requests-cache
